quasix-0.6.0.dist-info/METADATA
quasix-0.6.0.dist-info/WHEEL
quasix.libs/libaec-df4ff8a4.so.0
quasix.libs/libbrotlicommon-abf86ae9.so.1
quasix.libs/libbrotlidec-db9dbda7.so.1
quasix.libs/libcint-1f454b83.so.6
quasix.libs/libcom_err-a2b7c9d2.so.2
quasix.libs/libcrypto-ef58def3.so.3
quasix.libs/libcurl-ef05c8ea.so.4
quasix.libs/libffi-247da4d5.so.8
quasix.libs/libgfortran-3ec47101.so.5
quasix.libs/libgmp-4dc20a90.so.10
quasix.libs/libgnutls-a1c10edc.so.30
quasix.libs/libgssapi_krb5-74c938dc.so.2
quasix.libs/libhdf5_serial-12e4461a.so.103
quasix.libs/libhogweed-47d56894.so.6
quasix.libs/libidn2-1420c60a.so.0
quasix.libs/libk5crypto-43d6a714.so.3
quasix.libs/libkeyutils-ad20d5fb.so.1
quasix.libs/libkrb5-7ccebba4.so.3
quasix.libs/libkrb5support-134342ea.so.0
quasix.libs/liblber-2-a3ddec4a.5.so.0
quasix.libs/libldap-2-24e60f72.5.so.0
quasix.libs/libnettle-2d3bda6c.so.8
quasix.libs/libnghttp2-1cc16764.so.14
quasix.libs/libp11-kit-d2b01eaa.so.0
quasix.libs/libpsl-95ca960e.so.5
quasix.libs/libquadmath-67d31475.so.0
quasix.libs/librtmp-2401c4fc.so.1
quasix.libs/libsasl2-344870a9.so.2
quasix.libs/libssh-f4c6722f.so.4
quasix.libs/libssl-660a6abe.so.3
quasix.libs/libsz-53f3c9c7.so.2
quasix.libs/libtasn1-5982aae4.so.6
quasix.libs/libunistring-9c28d595.so.2
quasix.libs/libzstd-5df4f4df.so.1
quasix/__init__.py
quasix/__pycache__/__init__.cpython-310.pyc
quasix/__pycache__/bse_driver.cpython-310.pyc
quasix/__pycache__/correlation.cpython-310.pyc
quasix/__pycache__/correlation_batch.cpython-310.pyc
quasix/__pycache__/df_tensor.cpython-310.pyc
quasix/__pycache__/df_tensors.cpython-310.pyc
quasix/__pycache__/dielectric.cpython-310.pyc
quasix/__pycache__/evgw.cpython-310.pyc
quasix/__pycache__/freq.cpython-310.pyc
quasix/__pycache__/logging.cpython-310.pyc
quasix/__pycache__/mo_transform.cpython-310.pyc
quasix/__pycache__/monitoring.cpython-310.pyc
quasix/__pycache__/polarizability_update.cpython-310.pyc
quasix/__pycache__/qp.cpython-310.pyc
quasix/__pycache__/screening.cpython-310.pyc
quasix/__pycache__/selfenergy.cpython-310.pyc
quasix-0.6.0.dist-info/RECORD
