Metadata-Version: 2.4
Name: quasix
Version: 0.6.0
Classifier: Development Status :: 3 - Alpha
Classifier: Intended Audience :: Science/Research
Classifier: License :: OSI Approved :: MIT License
Classifier: License :: OSI Approved :: Apache Software License
Classifier: Operating System :: POSIX :: Linux
Classifier: Operating System :: MacOS
Classifier: Programming Language :: Python :: 3
Classifier: Programming Language :: Python :: 3.10
Classifier: Programming Language :: Python :: 3.11
Classifier: Programming Language :: Python :: 3.12
Classifier: Programming Language :: Rust
Classifier: Topic :: Scientific/Engineering :: Chemistry
Classifier: Topic :: Scientific/Engineering :: Physics
Requires-Dist: numpy>=1.24.0
Requires-Dist: scipy>=1.10.0
Requires-Dist: pyscf>=2.3.0
Requires-Dist: h5py>=3.8.0
Requires-Dist: matplotlib>=3.6.0
Requires-Dist: pytest>=7.2.0 ; extra == 'dev'
Requires-Dist: pytest-cov>=4.0.0 ; extra == 'dev'
Requires-Dist: pytest-benchmark>=4.0.0 ; extra == 'dev'
Requires-Dist: black>=23.0.0 ; extra == 'dev'
Requires-Dist: ruff>=0.1.0 ; extra == 'dev'
Requires-Dist: mypy>=1.0.0 ; extra == 'dev'
Requires-Dist: ipython>=8.0.0 ; extra == 'dev'
Requires-Dist: jupyter>=1.0.0 ; extra == 'dev'
Requires-Dist: pytest>=7.2.0 ; extra == 'test'
Requires-Dist: pytest-cov>=4.0.0 ; extra == 'test'
Requires-Dist: pytest-benchmark>=4.0.0 ; extra == 'test'
Requires-Dist: sphinx>=5.0.0 ; extra == 'docs'
Requires-Dist: sphinx-rtd-theme>=1.2.0 ; extra == 'docs'
Requires-Dist: nbsphinx>=0.9.0 ; extra == 'docs'
Provides-Extra: dev
Provides-Extra: test
Provides-Extra: docs
Summary: High-performance GW/BSE implementation with PySCF integration
Keywords: quantum chemistry,GW,BSE,many-body perturbation theory,pyscf,rust
Author-email: QuasiX Development Team <dev@quasix.org>
License: MIT OR Apache-2.0
Requires-Python: >=3.10
Project-URL: Homepage, https://github.com/ExaPsi/QuasiX
Project-URL: Documentation, https://quasix.readthedocs.io
Project-URL: Repository, https://github.com/ExaPsi/QuasiX
Project-URL: Issues, https://github.com/ExaPsi/QuasiX/issues
